pesapal_v3/__init__.py
pesapal_v3/__version__.py
pesapal_v3/_exceptions.py
pesapal_v3/_pesapal.py
pesapal_v3/_types.py
pesapal_v3-0.2.1.dist-info/METADATA
pesapal_v3-0.2.1.dist-info/WHEEL
pesapal_v3-0.2.1.dist-info/licenses/LICENSE
pesapal_v3-0.2.1.dist-info/RECORD
